<annotation verified="yes">
	<folder>eczema</folder>
	<filename>10 (168).jpg</filename>
	<path>C:\Users\Admin\Desktop\eczema\10 (168).jpg</path>
	<source>
		<database>Unknown</database>
	</source>
	<size>
		<width>3024</width>
		<height>4032</height>
		<depth>3</depth>
	</size>
	<segmented>0</segmented>
	<object>
		<name>Eczema</name>
		<pose>Unspecified</pose>
		<truncated>0</truncated>
		<difficult>0</difficult>
		<bndbox>
			<xmin>661</xmin>
			<ymin>833</ymin>
			<xmax>1896</xmax>
			<ymax>3338</ymax>
		</bndbox>
	</object>
</annotation>
